[{"arguments":["C:/Qt/Tools/mingw1120_64/bin/g++.exe","-c","--target=x86_64-w64-mingw32","-m64","-fno-keep-inline-dllexport","-O2","-g","-std=gnu++1z","-Wall","-Wextra","-Wextra","-fexceptions","-mthreads","-IC:/Users/maria/Desktop/Proyecto final/Video","-IC:/Qt/6.7.3/mingw_64/include","-IC:/Qt/6.7.3/mingw_64/include/QtMultimediaWidgets","-IC:/Qt/6.7.3/mingw_64/include/QtMultimedia","-IC:/Qt/6.7.3/mingw_64/include/QtWidgets","-IC:/Qt/6.7.3/mingw_64/include/QtGui","-IC:/Qt/6.7.3/mingw_64/include/QtNetwork","-IC:/Qt/6.7.3/mingw_64/include/QtCore","-IC:/Users/maria/Desktop/Proyecto final/Video/build/Desktop_Qt_6_7_3_MinGW_64_bit-Profile/release","-IC:/Users/maria/Desktop/Proyecto final/Video/build/Desktop_Qt_6_7_3_MinGW_64_bit-Profile","-IC:/Qt/6.7.3/mingw_64/mkspecs/win32-g++","-DUNICODE","-D_UNICODE","-DWIN32","-DMINGW_HAS_SECURE_API","-DQT_QML_DEBUG","-DQT_NO_DEBUG","-DQT_MULTIMEDIAWIDGETS_LIB","-DQT_MULTIMEDIA_LIB","-DQT_WIDGETS_LIB","-DQT_GUI_LIB","-DQT_NETWORK_LIB","-DQT_CORE_LIB","-DQT_NEEDS_QMAIN","-x","c++","C:\\Users\\maria\\Desktop\\Proyecto final\\Video\\main.cpp"],"directory":"C:/Users/maria/Desktop/Proyecto final/Video/build/Desktop_Qt_6_7_3_MinGW_64_bit-Profile","file":"C:/Users/maria/Desktop/Proyecto final/Video/main.cpp"},{"arguments":["C:/Qt/Tools/mingw1120_64/bin/g++.exe","-c","--target=x86_64-w64-mingw32","-m64","-fno-keep-inline-dllexport","-O2","-g","-std=gnu++1z","-Wall","-Wextra","-Wextra","-fexceptions","-mthreads","-IC:/Users/maria/Desktop/Proyecto final/Video","-IC:/Qt/6.7.3/mingw_64/include","-IC:/Qt/6.7.3/mingw_64/include/QtMultimediaWidgets","-IC:/Qt/6.7.3/mingw_64/include/QtMultimedia","-IC:/Qt/6.7.3/mingw_64/include/QtWidgets","-IC:/Qt/6.7.3/mingw_64/include/QtGui","-IC:/Qt/6.7.3/mingw_64/include/QtNetwork","-IC:/Qt/6.7.3/mingw_64/include/QtCore","-IC:/Users/maria/Desktop/Proyecto final/Video/build/Desktop_Qt_6_7_3_MinGW_64_bit-Profile/release","-IC:/Users/maria/Desktop/Proyecto final/Video/build/Desktop_Qt_6_7_3_MinGW_64_bit-Profile","-IC:/Qt/6.7.3/mingw_64/mkspecs/win32-g++","-DUNICODE","-D_UNICODE","-DWIN32","-DMINGW_HAS_SECURE_API","-DQT_QML_DEBUG","-DQT_NO_DEBUG","-DQT_MULTIMEDIAWIDGETS_LIB","-DQT_MULTIMEDIA_LIB","-DQT_WIDGETS_LIB","-DQT_GUI_LIB","-DQT_NETWORK_LIB","-DQT_CORE_LIB","-DQT_NEEDS_QMAIN","-x","c++","C:\\Users\\maria\\Desktop\\Proyecto final\\Video\\mainwindow.cpp"],"directory":"C:/Users/maria/Desktop/Proyecto final/Video/build/Desktop_Qt_6_7_3_MinGW_64_bit-Profile","file":"C:/Users/maria/Desktop/Proyecto final/Video/mainwindow.cpp"},{"arguments":["C:/Qt/Tools/mingw1120_64/bin/g++.exe","-c","--target=x86_64-w64-mingw32","-m64","-fno-keep-inline-dllexport","-O2","-g","-std=gnu++1z","-Wall","-Wextra","-Wextra","-fexceptions","-mthreads","-IC:/Users/maria/Desktop/Proyecto final/Video","-IC:/Qt/6.7.3/mingw_64/include","-IC:/Qt/6.7.3/mingw_64/include/QtMultimediaWidgets","-IC:/Qt/6.7.3/mingw_64/include/QtMultimedia","-IC:/Qt/6.7.3/mingw_64/include/QtWidgets","-IC:/Qt/6.7.3/mingw_64/include/QtGui","-IC:/Qt/6.7.3/mingw_64/include/QtNetwork","-IC:/Qt/6.7.3/mingw_64/include/QtCore","-IC:/Users/maria/Desktop/Proyecto final/Video/build/Desktop_Qt_6_7_3_MinGW_64_bit-Profile/release","-IC:/Users/maria/Desktop/Proyecto final/Video/build/Desktop_Qt_6_7_3_MinGW_64_bit-Profile","-IC:/Qt/6.7.3/mingw_64/mkspecs/win32-g++","-DUNICODE","-D_UNICODE","-DWIN32","-DMINGW_HAS_SECURE_API","-DQT_QML_DEBUG","-DQT_NO_DEBUG","-DQT_MULTIMEDIAWIDGETS_LIB","-DQT_MULTIMEDIA_LIB","-DQT_WIDGETS_LIB","-DQT_GUI_LIB","-DQT_NETWORK_LIB","-DQT_CORE_LIB","-DQT_NEEDS_QMAIN","-x","c++-header","C:\\Users\\maria\\Desktop\\Proyecto final\\Video\\mainwindow.h"],"directory":"C:/Users/maria/Desktop/Proyecto final/Video/build/Desktop_Qt_6_7_3_MinGW_64_bit-Profile","file":"C:/Users/maria/Desktop/Proyecto final/Video/mainwindow.h"},{"arguments":["C:/Qt/Tools/mingw1120_64/bin/g++.exe","-c","--target=x86_64-w64-mingw32","-m64","-fno-keep-inline-dllexport","-O2","-g","-std=gnu++1z","-Wall","-Wextra","-Wextra","-fexceptions","-mthreads","-IC:/Users/maria/Desktop/Proyecto final/Video","-IC:/Qt/6.7.3/mingw_64/include","-IC:/Qt/6.7.3/mingw_64/include/QtMultimediaWidgets","-IC:/Qt/6.7.3/mingw_64/include/QtMultimedia","-IC:/Qt/6.7.3/mingw_64/include/QtWidgets","-IC:/Qt/6.7.3/mingw_64/include/QtGui","-IC:/Qt/6.7.3/mingw_64/include/QtNetwork","-IC:/Qt/6.7.3/mingw_64/include/QtCore","-IC:/Users/maria/Desktop/Proyecto final/Video/build/Desktop_Qt_6_7_3_MinGW_64_bit-Profile/release","-IC:/Users/maria/Desktop/Proyecto final/Video/build/Desktop_Qt_6_7_3_MinGW_64_bit-Profile","-IC:/Qt/6.7.3/mingw_64/mkspecs/win32-g++","-DUNICODE","-D_UNICODE","-DWIN32","-DMINGW_HAS_SECURE_API","-DQT_QML_DEBUG","-DQT_NO_DEBUG","-DQT_MULTIMEDIAWIDGETS_LIB","-DQT_MULTIMEDIA_LIB","-DQT_WIDGETS_LIB","-DQT_GUI_LIB","-DQT_NETWORK_LIB","-DQT_CORE_LIB","-DQT_NEEDS_QMAIN","-x","c++-header","C:\\Users\\maria\\Desktop\\Proyecto final\\Video\\ui_mainwindow.h"],"directory":"C:/Users/maria/Desktop/Proyecto final/Video/build/Desktop_Qt_6_7_3_MinGW_64_bit-Profile","file":"C:/Users/maria/Desktop/Proyecto final/Video/ui_mainwindow.h"},{"arguments":["C:/Qt/Tools/mingw1120_64/bin/g++.exe","-c","--target=x86_64-w64-mingw32","-m64","-fno-keep-inline-dllexport","-O2","-g","-std=gnu++1z","-Wall","-Wextra","-Wextra","-fexceptions","-mthreads","-IC:/Users/maria/Desktop/Proyecto final/Video","-IC:/Qt/6.7.3/mingw_64/include","-IC:/Qt/6.7.3/mingw_64/include/QtMultimediaWidgets","-IC:/Qt/6.7.3/mingw_64/include/QtMultimedia","-IC:/Qt/6.7.3/mingw_64/include/QtWidgets","-IC:/Qt/6.7.3/mingw_64/include/QtGui","-IC:/Qt/6.7.3/mingw_64/include/QtNetwork","-IC:/Qt/6.7.3/mingw_64/include/QtCore","-IC:/Users/maria/Desktop/Proyecto final/Video/build/Desktop_Qt_6_7_3_MinGW_64_bit-Profile/release","-IC:/Users/maria/Desktop/Proyecto final/Video/build/Desktop_Qt_6_7_3_MinGW_64_bit-Profile","-IC:/Qt/6.7.3/mingw_64/mkspecs/win32-g++","-DUNICODE","-D_UNICODE","-DWIN32","-DMINGW_HAS_SECURE_API","-DQT_QML_DEBUG","-DQT_NO_DEBUG","-DQT_MULTIMEDIAWIDGETS_LIB","-DQT_MULTIMEDIA_LIB","-DQT_WIDGETS_LIB","-DQT_GUI_LIB","-DQT_NETWORK_LIB","-DQT_CORE_LIB","-DQT_NEEDS_QMAIN","-x","c++-header","C:\\Users\\maria\\Desktop\\Proyecto final\\Video\\build\\Desktop_Qt_6_7_3_MinGW_64_bit-Profile\\ui_mainwindow.h"],"directory":"C:/Users/maria/Desktop/Proyecto final/Video/build/Desktop_Qt_6_7_3_MinGW_64_bit-Profile","file":"C:/Users/maria/Desktop/Proyecto final/Video/build/Desktop_Qt_6_7_3_MinGW_64_bit-Profile/ui_mainwindow.h"}]